lkg_pack/__init__.py
lkg_pack/main.py
lkg_pack-0.1.dist-info/METADATA
lkg_pack-0.1.dist-info/WHEEL
lkg_pack-0.1.dist-info/top_level.txt
lkg_pack-0.1.dist-info/RECORD
