Metadata-Version: 2.1
Name: lkg_pack
Version: 0.1
